chinoscriba/__init__.py
chinoscriba/api_client.py
chinoscriba/configuration.py
chinoscriba/rest.py
chinoscriba/api/__init__.py
chinoscriba/api/blocks_api.py
chinoscriba/api/events_api.py
chinoscriba/api/logs_api.py
chinoscriba/api/stats_api.py
chinoscriba/models/__init__.py
chinoscriba/models/audit_log.py
chinoscriba/models/block.py
chinoscriba/models/event.py
chinoscriba/models/inline_response200.py
chinoscriba/models/inline_response2001.py
chinoscriba/models/inline_response2002.py
chinoscriba/models/inline_response200_bis.py
chinoscriba/models/log.py
chinoscriba/models/multi_audit_log_serializer_output.py
chinoscriba/models/search_request.py
chinoscriba/models/sort_rule.py
chinoscriba/models/stat.py
chinoscriba/models/validate_block.py
chinoscriba/models/validate_block_response.py
test/__init__.py
test/test_default_api.py
test/utils.py
chinoscriba-2.2.0.dist-info/METADATA
chinoscriba-2.2.0.dist-info/WHEEL
chinoscriba-2.2.0.dist-info/top_level.txt
chinoscriba-2.2.0.dist-info/RECORD
