Metadata-Version: 2.1
Name: chinoscriba
Version: 2.2.0
Summary: Chino.io Scriba SDK Python
Home-page: https://www.chino.io
Author-email: 
License: UNKNOWN
Keywords: Chino.io Scriba API
Platform: UNKNOWN
Classifier: Topic :: Software Development
Classifier: Development Status :: 5 - Production/Stable
Classifier: Programming Language :: Python :: 2
Classifier: Programming Language :: Python :: 3
Requires-Dist: urllib3>=1.15
Requires-Dist: six>=1.10
Requires-Dist: certifi
Requires-Dist: python-dateutil
